interplot/__init__.py
interplot/arraytools.py
interplot/conf.py
interplot/iter.py
interplot/plot.py
interplot-1.0.0.dist-info/.DS_Store
interplot-1.0.0.dist-info/LICENCE.txt
interplot-1.0.0.dist-info/METADATA
interplot-1.0.0.dist-info/WHEEL
interplot-1.0.0.dist-info/top_level.txt
interplot-1.0.0.dist-info/RECORD
