Metadata-Version: 2.1
Name: interplot
Version: 1.0.0
Summary: Create matplotlib and plotly charts with the same few lines of code.
Home-page: https://github.com/janjoch/interplot
Author: Janosch Jörg
Author-email: janjo@duck.com
License: GPL v3
Classifier: Development Status :: 3 - Alpha
Classifier: Intended Audience :: Science/Research
Classifier: License :: OSI Approved :: GNU General Public License v3 (GPLv3)
Classifier: Operating System :: MacOS :: MacOS X
Classifier: Operating System :: Microsoft :: Windows
Classifier: Programming Language :: Python :: 3
Classifier: Programming Language :: Python :: 3.6
Classifier: Programming Language :: Python :: 3.7
Classifier: Programming Language :: Python :: 3.8
License-File: LICENCE.txt
Requires-Dist: numba
Requires-Dist: numpy
Requires-Dist: pandas
Requires-Dist: matplotlib
Requires-Dist: plotly
Requires-Dist: kaleido
Requires-Dist: scipy
Requires-Dist: xarray
